{
  "group_name": "Number of Arms Included",
  "columns": [
    {
      "column_index": 1,
      "column_name": "Number of Arms Included",
      "found_in_pdf": true,
      "page": 1,
      "source_type": "text",
      "confidence": "high",
      "extraction_plan": "The study is described as a \"2 x 2 factorial design\". This indicates two factors, each with two levels, resulting in 4 arms. The arms are: standard of care (n=296), standard of care plus radiotherapy (n=293), standard of care plus abiraterone (n=292), or standard of care plus radiotherapy plus abiraterone (n=291).",
      "column_name_raw": null
    }
  ]
}