{
  "group_name": "Adverse Events - N (%)",
  "columns": [
    {
      "column_index": 1,
      "column_name": "Adverse Events - N (%) | All-Cause Grade 3 or Higher | Treatment",
      "found_in_pdf": true,
      "page": 9,
      "source_type": "table",
      "sources": [
        [
          9,
          "table"
        ],
        [
          1,
          "text"
        ],
        [
          4,
          "text"
        ]
      ],
      "confidence": "high",
      "extraction_plan": "Sum the N and % values for 'Grade 3', 'Grade 4', and 'Grade 5 (death)' under the 'Worst grade' section for 'Darolutamide (n = 652)' in the 'All Patients' column of Table 3 on page 9. Grade 3: 248 (38.0%), Grade 4: 183 (28.1%), Grade 5 (death): 27 (4.1%). Total N = 248 + 183 + 27 = 458. Total % = 38.0 + 28.1 + 4.1 = 70.2%. Value: 458 (70.2%).",
      "column_name_raw": null
    },
    {
      "column_index": 2,
      "column_name": "Adverse Events - N (%) | All-Cause Grade 3 or Higher | Control",
      "found_in_pdf": true,
      "page": 9,
      "source_type": "table",
      "sources": [
        [
          9,
          "table"
        ],
        [
          1,
          "text"
        ],
        [
          4,
          "text"
        ]
      ],
      "confidence": "high",
      "extraction_plan": "Sum the N and % values for 'Grade 3', 'Grade 4', and 'Grade 5 (death)' under the 'Worst grade' section for 'Placebo (n = 650)' in the 'All Patients' column of Table 3 on page 9. Grade 3: 232 (35.7%), Grade 4: 181 (27.8%), Grade 5 (death): 26 (4.0%). Total N = 232 + 181 + 26 = 439. Total % = 35.7 + 27.8 + 4.0 = 67.5%. Value: 439 (67.5%).",
      "column_name_raw": null
    },
    {
      "column_index": 3,
      "column_name": "Adverse Events - N (%) | Treatment-related Grade 3 or Higher | Treatment",
      "found_in_pdf": false,
      "page": -1,
      "source_type": "not_applicable",
      "sources": [
        [
          9,
          "table"
        ],
        [
          1,
          "text"
        ],
        [
          4,
          "text"
        ]
      ],
      "confidence": "high",
      "extraction_plan": "Table 3 on page 9 provides 'Worst grade' for all AEs, but does not differentiate between all-cause and treatment-related AEs for Grade 3 or higher. The abstract and safety sections on pages 1 and 4 also do not provide this specific breakdown.",
      "column_name_raw": null
    },
    {
      "column_index": 4,
      "column_name": "Adverse Events - N (%) | Treatment-related Grade 3 or Higher | Control",
      "found_in_pdf": false,
      "page": -1,
      "source_type": "not_applicable",
      "sources": [
        [
          9,
          "table"
        ],
        [
          1,
          "text"
        ],
        [
          4,
          "text"
        ]
      ],
      "confidence": "high",
      "extraction_plan": "Table 3 on page 9 provides 'Worst grade' for all AEs, but does not differentiate between all-cause and treatment-related AEs for Grade 3 or higher. The abstract and safety sections on pages 1 and 4 also do not provide this specific breakdown.",
      "column_name_raw": null
    },
    {
      "column_index": 5,
      "column_name": "Adverse Events - N (%) | Treatment-related Grade 5 | Treatment",
      "found_in_pdf": false,
      "page": -1,
      "source_type": "not_applicable",
      "sources": [
        [
          9,
          "table"
        ],
        [
          1,
          "text"
        ],
        [
          4,
          "text"
        ]
      ],
      "confidence": "high",
      "extraction_plan": "Table 3 on page 9 lists 'Grade 5 (death)' for all AEs, but does not specify if these are treatment-related. The footnote 'd' indicates specific grade 5 events are in the supplementary appendix, which is not provided in detail for this specific query. The text on pages 1 and 4 does not provide this information.",
      "column_name_raw": null
    },
    {
      "column_index": 6,
      "column_name": "Adverse Events - N (%) | Treatment-related Grade 5 | Control",
      "found_in_pdf": false,
      "page": -1,
      "source_type": "not_applicable",
      "sources": [
        [
          9,
          "table"
        ],
        [
          1,
          "text"
        ],
        [
          4,
          "text"
        ]
      ],
      "confidence": "high",
      "extraction_plan": "Table 3 on page 9 lists 'Grade 5 (death)' for all AEs, but does not specify if these are treatment-related. The footnote 'd' indicates specific grade 5 events are in the supplementary appendix, which is not provided in detail for this specific query. The text on pages 1 and 4 does not provide this information.",
      "column_name_raw": null
    }
  ]
}