{
  "total_groups": 38,
  "total_columns": 129,
  "plans": [
    {
      "group_name": "Add-on Treatment",
      "columns": [
        {
          "column_index": 1,
          "column_name": "Add-on Treatment",
          "found_in_pdf": true,
          "page": 1,
          "source_type": "text",
          "confidence": "high",
          "extraction_plan": "The add-on treatments are 'abiraterone acetate plus prednisolone' (referred to as abiraterone) and 'abiraterone acetate and prednisolone plus enzalutamide'. This information is explicitly stated in the 'Summary' and 'Methods' sections on page 1, and further referenced in the 'Introduction' on page 2 and in the column headers of Table 1 on pages 5-6 and Table 2 on page 10, as well as Figures 2 and 4 on pages 8-9.",
          "column_name_raw": null
        }
      ]
    },
    {
      "group_name": "Control Arm",
      "columns": [
        {
          "column_index": 1,
          "column_name": "Control Arm",
          "found_in_pdf": true,
          "page": 1,
          "source_type": "text",
          "confidence": "high",
          "extraction_plan": "The control arm is defined as \"standard of care (androgen deprivation therapy; docetaxel 75 mg/m\u00b2 intravenously for six cycles with prednisolone 10 mg orally once per day allowed from Dec 17, 2015)\" in the Methods section on page 1. It is also referred to as \"standard of care (control group)\" in the Randomisation and masking section on page 3. In Table 1 (pages 5 and 6), it is listed as \"Standard of care\" with sample sizes (n=502 for Abiraterone trial, n=454 for Abiraterone and Enzalutamide trial).",
          "column_name_raw": null
        }
      ]
    },
    {
      "group_name": "Control Arm - N",
      "columns": [
        {
          "column_index": 1,
          "column_name": "Control Arm - N",
          "found_in_pdf": true,
          "page": 5,
          "source_type": "table",
          "confidence": "high",
          "extraction_plan": "Extract the 'n' value from the column header 'Standard of care (n=502)' in Table 1 on page 5 for the Abiraterone trial. The document also reports a control arm for the Abiraterone and Enzalutamide trial with n=454, found in Table 1 on page 6 and in the 'Findings' text on page 1.",
          "column_name_raw": null
        }
      ]
    },
    {
      "group_name": "Median Follow-Up Duration (mo)",
      "columns": [
        {
          "column_index": 1,
          "column_name": "Median Follow-Up Duration (mo)",
          "found_in_pdf": true,
          "page": 1,
          "source_type": "text",
          "confidence": "high",
          "extraction_plan": "Extract '96 months' (IQR 86\u2013107) for the abiraterone trial and '72 months' (61\u201374) for the abiraterone and enzalutamide trial from the 'Findings' section on page 1.",
          "column_name_raw": null
        }
      ]
    },
    {
      "group_name": "ID",
      "columns": [
        {
          "column_index": 1,
          "column_name": "NCT",
          "found_in_pdf": true,
          "page": 1,
          "source_type": "text",
          "confidence": "high",
          "extraction_plan": "Extract the NCT number 'NCT00268476' from the 'Methods' section on page 1, which states 'STAMPEDE is registered with ClinicalTrials.gov (NCT00268476) and ISRCTN (ISRCTN78818544)'.",
          "column_name_raw": null
        },
        {
          "column_index": 2,
          "column_name": "PubMed ID",
          "found_in_pdf": false,
          "page": -1,
          "source_type": "not_applicable",
          "confidence": "high",
          "extraction_plan": "The PubMed ID is not reported within the provided PDF content. It would typically be assigned by PubMed upon indexing the article.",
          "column_name_raw": null
        },
        {
          "column_index": 3,
          "column_name": "Trial Name",
          "found_in_pdf": true,
          "page": 1,
          "source_type": "text",
          "confidence": "high",
          "extraction_plan": "Extract the main title of the article on page 1: 'Abiraterone acetate plus prednisolone with or without enzalutamide for patients with metastatic prostate cancer starting androgen deprivation therapy: final results from two randomised phase 3 trials of the STAMPEDE platform protocol'.",
          "column_name_raw": null
        },
        {
          "column_index": 4,
          "column_name": "Author",
          "found_in_pdf": true,
          "page": 1,
          "source_type": "text",
          "confidence": "high",
          "extraction_plan": "Extract the list of authors from the author byline on page 1, starting with 'Gerhardt Attard' and ending with 'Nicholas D James\u2020, for the STAMPEDE investigators\u2021'.",
          "column_name_raw": null
        },
        {
          "column_index": 5,
          "column_name": "Year",
          "found_in_pdf": true,
          "page": 1,
          "source_type": "text",
          "confidence": "high",
          "extraction_plan": "Extract the year '2023' from the journal citation 'Lancet Oncol 2023' at the top right of page 1 or from the footer 'Vol 24 May 2023' on any page.",
          "column_name_raw": null
        },
        {
          "column_index": 6,
          "column_name": "Full Pub or Abstract",
          "found_in_pdf": true,
          "page": 1,
          "source_type": "text",
          "confidence": "high",
          "extraction_plan": "The document is a full publication, as indicated by its comprehensive structure, multiple sections (Summary, Methods, Findings, Interpretation, etc.), and length across several pages.",
          "column_name_raw": null
        },
        {
          "column_index": 7,
          "column_name": "Phase",
          "found_in_pdf": true,
          "page": 1,
          "source_type": "text",
          "confidence": "high",
          "extraction_plan": "Extract 'phase 3' from the title of the article on page 1: 'final results from two randomised phase 3 trials'.",
          "column_name_raw": null
        },
        {
          "column_index": 8,
          "column_name": "Original/Follow Up",
          "found_in_pdf": true,
          "page": 1,
          "source_type": "text",
          "confidence": "high",
          "extraction_plan": "The title on page 1 states 'final results' and the 'Summary' section on page 1 mentions 'evaluate long-term outcomes'. The 'Introduction' on page 2 further clarifies 'The STAMPEDE abiraterone trial has now closed, 10 years after initiation of accrual, providing the opportunity to assess new data on long-term efficacy', indicating this is a follow-up publication.",
          "column_name_raw": null
        }
      ]
    },
    {
      "group_name": "Median Age (years)",
      "columns": [
        {
          "column_index": 1,
          "column_name": "Median Age (years) | Treatment",
          "found_in_pdf": true,
          "page": 5,
          "source_type": "table",
          "confidence": "high",
          "extraction_plan": "Locate Table 1 on page 5. In the 'Age, years' row, extract the 'Median' value from the 'Abiraterone trial: Standard of care plus abiraterone (n=501)' column and the 'Abiraterone and enzalutamide trial: Standard of care plus enzalutamide and abiraterone (n=462)' column.",
          "column_name_raw": null
        },
        {
          "column_index": 2,
          "column_name": "Median Age (years) | Control",
          "found_in_pdf": true,
          "page": 5,
          "source_type": "table",
          "confidence": "high",
          "extraction_plan": "Locate Table 1 on page 5. In the 'Age, years' row, extract the 'Median' value from the 'Abiraterone trial: Standard of care (n=502)' column and the 'Abiraterone and enzalutamide trial: Standard of care (n=454)' column.",
          "column_name_raw": null
        }
      ]
    },
    {
      "group_name": "Class of Agent in Treatment Arm 1",
      "columns": [
        {
          "column_index": 1,
          "column_name": "Class of Agent in Treatment Arm 1",
          "found_in_pdf": true,
          "page": 11,
          "source_type": "text",
          "confidence": "high",
          "extraction_plan": "The document describes two main experimental arms. Assuming 'Treatment Arm 1' refers to the first experimental arm introduced, this would be the abiraterone trial's experimental arm. The agent in this arm is 'abiraterone acetate and prednisolone' (page 1, Methods). The class of abiraterone acetate is an androgen synthesis inhibitor. This is implicitly derived from the 'Discussion' section on page 11, which contrasts abiraterone with 'androgen receptor antagonists' (like enzalutamide) and discusses its effect on 'androgens'.",
          "column_name_raw": null
        }
      ]
    },
    {
      "group_name": "Median On-Treatment Duration (mo)",
      "columns": [
        {
          "column_index": 1,
          "column_name": "Median On-Treatment Duration (mo) | Treatment",
          "found_in_pdf": false,
          "page": -1,
          "source_type": "not_applicable",
          "confidence": "high",
          "extraction_plan": "The median on-treatment duration for the treatment group was not explicitly reported in the PDF. The document mentions 'median follow-up' (pages 1, 2, 6) and 'time from randomisation to starting treatment' (page 6), and reasons for 'stopping treatment' (page 11), but not the median duration of the treatment itself.",
          "column_name_raw": null
        },
        {
          "column_index": 2,
          "column_name": "Median On-Treatment Duration (mo) | Control",
          "found_in_pdf": false,
          "page": -1,
          "source_type": "not_applicable",
          "confidence": "high",
          "extraction_plan": "The median on-treatment duration for the control group was not explicitly reported in the PDF. The document mentions 'median follow-up' (pages 1, 2, 6) and 'time from randomisation to starting treatment' (page 6), and reasons for 'stopping treatment' (page 11), but not the median duration of the treatment itself.",
          "column_name_raw": null
        }
      ]
    },
    {
      "group_name": "COE_RCT_IND_OVERALL_RJ",
      "columns": [
        {
          "column_index": 1,
          "column_name": "COE_RCT_IND_OVERALL_RJ",
          "found_in_pdf": true,
          "page": 1,
          "source_type": "text",
          "confidence": "high",
          "extraction_plan": "Extract the interaction Hazard Ratio (HR) and its 95% confidence interval and p-value, which compares the treatment effect between the abiraterone trial and the abiraterone and enzalutamide trial, as reported in the 'Findings' section on page 1. The value is 'HR 1\u00b705 (95% CI 0\u00b783\u20131\u00b732); pinteraction=0\u00b771'.",
          "column_name_raw": null
        }
      ]
    },
    {
      "group_name": "Median PFS (mo)",
      "columns": [
        {
          "column_index": 1,
          "column_name": "Median PFS (mo) | Overall | Treatment",
          "found_in_pdf": false,
          "page": 9,
          "source_type": "not_applicable",
          "confidence": "low",
          "extraction_plan": "Median Progression-Free Survival (PFS) in months for the overall treatment group is not explicitly reported in the main document. Figure 4C and 4D on page 9 show Kaplan-Meier curves for failure-free survival, which is a secondary outcome related to PFS, but do not provide explicit median values. The text on page 11 mentions HRs for PFS but not median durations. The appendix (pp 5, 18, 19) is cited for more details, but is not available.",
          "column_name_raw": null
        },
        {
          "column_index": 2,
          "column_name": "Median PFS (mo) | Overall | Control",
          "found_in_pdf": false,
          "page": 9,
          "source_type": "not_applicable",
          "confidence": "low",
          "extraction_plan": "Median Progression-Free Survival (PFS) in months for the overall control group is not explicitly reported in the main document. Figure 4C and 4D on page 9 show Kaplan-Meier curves for failure-free survival, which is a secondary outcome related to PFS, but do not provide explicit median values. The text on page 11 mentions HRs for PFS but not median durations. The appendix (pp 5, 18, 19) is cited for more details, but is not available.",
          "column_name_raw": null
        },
        {
          "column_index": 3,
          "column_name": "Median PFS (mo) | High volume | Treatment",
          "found_in_pdf": false,
          "page": 9,
          "source_type": "not_applicable",
          "confidence": "low",
          "extraction_plan": "Median Progression-Free Survival (PFS) in months for the high volume treatment group is not explicitly reported in the main document. Figure 4E and 4F on page 9 show Kaplan-Meier curves for metastatic progression-free survival, which is a secondary outcome related to PFS, but do not provide explicit median values. The text on page 11 mentions HRs for PFS but not median durations. The appendix (pp 5, 18, 19) is cited for more details, but is not available.",
          "column_name_raw": null
        },
        {
          "column_index": 4,
          "column_name": "Median PFS (mo) | High volume | Control",
          "found_in_pdf": false,
          "page": 9,
          "source_type": "not_applicable",
          "confidence": "low",
          "extraction_plan": "Median Progression-Free Survival (PFS) in months for the high volume control group is not explicitly reported in the main document. Figure 4E and 4F on page 9 show Kaplan-Meier curves for metastatic progression-free survival, which is a secondary outcome related to PFS, but do not provide explicit median values. The text on page 11 mentions HRs for PFS but not median durations. The appendix (pp 5, 18, 19) is cited for more details, but is not available.",
          "column_name_raw": null
        },
        {
          "column_index": 5,
          "column_name": "Median PFS (mo) | Low volume | Treatment",
          "found_in_pdf": false,
          "page": 9,
          "source_type": "not_applicable",
          "confidence": "low",
          "extraction_plan": "Median Progression-Free Survival (PFS) in months for the low volume treatment group is not explicitly reported in the main document. Figure 4E and 4F on page 9 show Kaplan-Meier curves for metastatic progression-free survival, which is a secondary outcome related to PFS, but do not provide explicit median values. The text on page 11 mentions HRs for PFS but not median durations. The appendix (pp 5, 18, 19) is cited for more details, but is not available.",
          "column_name_raw": null
        },
        {
          "column_index": 6,
          "column_name": "Median PFS (mo) | Low volume | Control",
          "found_in_pdf": false,
          "page": 9,
          "source_type": "not_applicable",
          "confidence": "low",
          "extraction_plan": "Median Progression-Free Survival (PFS) in months for the low volume control group is not explicitly reported in the main document. Figure 4E and 4F on page 9 show Kaplan-Meier curves for metastatic progression-free survival, which is a secondary outcome related to PFS, but do not provide explicit median values. The text on page 11 mentions HRs for PFS but not median durations. The appendix (pp 5, 18, 19) is cited for more details, but is not available.",
          "column_name_raw": null
        }
      ]
    },
    {
      "group_name": "Docetaxel administration - N (%)",
      "columns": [
        {
          "column_index": 1,
          "column_name": "Docetaxel administration - N (%) | Treatment",
          "found_in_pdf": false,
          "page": 6,
          "source_type": "not_applicable",
          "confidence": "high",
          "extraction_plan": "The N (%) for docetaxel administration (specifically, 'Docetaxel planned as standard of care') for the combined 'Treatment' group across both trials is not explicitly reported. Table 1 on page 6 provides this data separately for each trial's treatment arm: 0 (0%) for the Abiraterone trial (n=501) and 41 (9%) for the Abiraterone and Enzalutamide trial (n=462).",
          "column_name_raw": null
        },
        {
          "column_index": 2,
          "column_name": "Docetaxel administration - N (%) | Control",
          "found_in_pdf": false,
          "page": 6,
          "source_type": "not_applicable",
          "confidence": "high",
          "extraction_plan": "The N (%) for docetaxel administration (specifically, 'Docetaxel planned as standard of care') for the combined 'Control' group across both trials is not explicitly reported. Table 1 on page 6 provides this data separately for each trial's control arm: 0 (0%) for the Abiraterone trial (n=502) and 39 (9%) for the Abiraterone and Enzalutamide trial (n=454).",
          "column_name_raw": null
        }
      ]
    },
    {
      "group_name": "Mode of metastases - N (%)",
      "columns": [
        {
          "column_index": 1,
          "column_name": "Mode of metastases - N (%) | Synchronous | Treatment",
          "found_in_pdf": false,
          "page": -1,
          "source_type": "not_applicable",
          "confidence": "high",
          "extraction_plan": "The document discusses metastatic prostate cancer patients and their characteristics (e.g., metastatic volume, N stage) in Table 1 (pages 5-6) and the Methods section (pages 1, 3). However, it does not explicitly report the 'Mode of metastases' categorized as 'Synchronous' for the treatment group. This specific breakdown was not found.",
          "column_name_raw": null
        },
        {
          "column_index": 2,
          "column_name": "Mode of metastases - N (%) | Synchronous | Control",
          "found_in_pdf": false,
          "page": -1,
          "source_type": "not_applicable",
          "confidence": "high",
          "extraction_plan": "The document discusses metastatic prostate cancer patients and their characteristics (e.g., metastatic volume, N stage) in Table 1 (pages 5-6) and the Methods section (pages 1, 3). However, it does not explicitly report the 'Mode of metastases' categorized as 'Synchronous' for the control group. This specific breakdown was not found.",
          "column_name_raw": null
        },
        {
          "column_index": 3,
          "column_name": "Mode of metastases - N (%) | Metachronous | Treatment",
          "found_in_pdf": false,
          "page": -1,
          "source_type": "not_applicable",
          "confidence": "high",
          "extraction_plan": "The document discusses metastatic prostate cancer patients and their characteristics (e.g., metastatic volume, N stage) in Table 1 (pages 5-6) and the Methods section (pages 1, 3). However, it does not explicitly report the 'Mode of metastases' categorized as 'Metachronous' for the treatment group. This specific breakdown was not found.",
          "column_name_raw": null
        },
        {
          "column_index": 4,
          "column_name": "Mode of metastases - N (%) | Metachronous | Control",
          "found_in_pdf": false,
          "page": -1,
          "source_type": "not_applicable",
          "confidence": "high",
          "extraction_plan": "The document discusses metastatic prostate cancer patients and their characteristics (e.g., metastatic volume, N stage) in Table 1 (pages 5-6) and the Methods section (pages 1, 3). However, it does not explicitly report the 'Mode of metastases' categorized as 'Metachronous' for the control group. This specific breakdown was not found.",
          "column_name_raw": null
        }
      ]
    },
    {
      "group_name": "Median OS (mo)",
      "columns": [
        {
          "column_index": 1,
          "column_name": "Median OS (mo) | Overall | Treatment",
          "found_in_pdf": true,
          "page": 1,
          "source_type": "text",
          "confidence": "high",
          "extraction_plan": "Extract the median overall survival for the abiraterone group in the abiraterone trial from the 'Findings' section on page 1: 'median overall survival was 76\u00b76 months'.",
          "column_name_raw": null
        },
        {
          "column_index": 2,
          "column_name": "Median OS (mo) | Overall | Control",
          "found_in_pdf": true,
          "page": 1,
          "source_type": "text",
          "confidence": "high",
          "extraction_plan": "Extract the median overall survival for the standard of care group in the abiraterone trial from the 'Findings' section on page 1: 'versus 45\u00b77 months'.",
          "column_name_raw": null
        },
        {
          "column_index": 3,
          "column_name": "Median OS (mo) | High volume | Treatment",
          "found_in_pdf": true,
          "page": 8,
          "source_type": "figure",
          "confidence": "high",
          "extraction_plan": "Locate Figure 3, panel E ('High-volume disease'). In the 'Overall' row, under the 'Study drug treatment' column, extract the 'Median overall survival, months' value: '54'.",
          "column_name_raw": null
        },
        {
          "column_index": 4,
          "column_name": "Median OS (mo) | High volume | Control",
          "found_in_pdf": true,
          "page": 8,
          "source_type": "figure",
          "confidence": "high",
          "extraction_plan": "Locate Figure 3, panel E ('High-volume disease'). In the 'Overall' row, under the 'Standard of care' column, extract the 'Median overall survival, months' value: '37'.",
          "column_name_raw": null
        },
        {
          "column_index": 5,
          "column_name": "Median OS (mo) | Low volume | Treatment",
          "found_in_pdf": true,
          "page": 8,
          "source_type": "figure",
          "confidence": "high",
          "extraction_plan": "Locate Figure 3, panel D ('Low-volume disease'). In the 'Overall' row, under the 'Study drug treatment' column, extract the 'Median overall survival, months' value: '97'.",
          "column_name_raw": null
        },
        {
          "column_index": 6,
          "column_name": "Median OS (mo) | Low volume | Control",
          "found_in_pdf": true,
          "page": 8,
          "source_type": "figure",
          "confidence": "high",
          "extraction_plan": "Locate Figure 3, panel D ('Low-volume disease'). In the 'Overall' row, under the 'Standard of care' column, extract the 'Median overall survival, months' value: '65'.",
          "column_name_raw": null
        }
      ]
    },
    {
      "group_name": "Adverse Events - N (%)",
      "columns": [
        {
          "column_index": 1,
          "column_name": "Adverse Events - N (%) | All-Cause Grade 3 or Higher | Treatment",
          "found_in_pdf": true,
          "page": 1,
          "source_type": "text",
          "confidence": "high",
          "extraction_plan": "Extract the number and percentage for 'grade 3-5 toxic effects' for the 'abiraterone and enzalutamide' treatment group from the 'Findings' section on page 1: '302 [68%] of 445'. This is explicitly stated as the 'highest toxic effects'.",
          "column_name_raw": null
        },
        {
          "column_index": 2,
          "column_name": "Adverse Events - N (%) | All-Cause Grade 3 or Higher | Control",
          "found_in_pdf": true,
          "page": 1,
          "source_type": "text",
          "confidence": "high",
          "extraction_plan": "Extract the number and percentage for 'grade 3-5 toxic effects' for the 'standard of care' group in the 'abiraterone and enzalutamide' trial from the 'Findings' section on page 1: '204 [45%] of 454'.",
          "column_name_raw": null
        },
        {
          "column_index": 3,
          "column_name": "Adverse Events - N (%) | Treatment-related Grade 3 or Higher | Treatment",
          "found_in_pdf": false,
          "page": 10,
          "source_type": "not_applicable",
          "confidence": "high",
          "extraction_plan": "The PDF reports 'grade 3-5 toxic effects' (all-cause) in the 'Findings' section on page 1 and 'Results' section on page 10, and detailed adverse events by grade in Table 2 on page 10. However, it does not provide a total N (%) specifically for 'treatment-related Grade 3 or Higher' adverse events.",
          "column_name_raw": null
        },
        {
          "column_index": 4,
          "column_name": "Adverse Events - N (%) | Treatment-related Grade 3 or Higher | Control",
          "found_in_pdf": false,
          "page": 10,
          "source_type": "not_applicable",
          "confidence": "high",
          "extraction_plan": "The PDF reports 'grade 3-5 toxic effects' (all-cause) in the 'Findings' section on page 1 and 'Results' section on page 10, and detailed adverse events by grade in Table 2 on page 10. However, it does not provide a total N (%) specifically for 'treatment-related Grade 3 or Higher' adverse events for the control group.",
          "column_name_raw": null
        },
        {
          "column_index": 5,
          "column_name": "Adverse Events - N (%) | Treatment-related Grade 5 | Treatment",
          "found_in_pdf": true,
          "page": 11,
          "source_type": "text",
          "confidence": "high",
          "extraction_plan": "Extract the number of deaths 'attributed to treatment' from the 'Discussion' section on page 11: 'two attributed to treatment' for the 'standard of care plus abiraterone and enzalutamide' group. The total N for this group is 445, so the percentage is (2/445) * 100 = 0.45%.",
          "column_name_raw": null
        },
        {
          "column_index": 6,
          "column_name": "Adverse Events - N (%) | Treatment-related Grade 5 | Control",
          "found_in_pdf": false,
          "page": 11,
          "source_type": "not_applicable",
          "confidence": "high",
          "extraction_plan": "The 'Discussion' section on page 11 mentions 'one (<1%) with standard of care in the abiraterone trial' for cardiac causes of death. However, it does not specify if this death was 'attributed to treatment', unlike the treatment group where it explicitly states 'two attributed to treatment'. Therefore, a specific N (%) for 'treatment-related Grade 5' for the control group is not reported.",
          "column_name_raw": null
        }
      ]
    },
    {
      "group_name": "Primary Endpoint(s)",
      "columns": [
        {
          "column_index": 1,
          "column_name": "Primary Endpoint(s)",
          "found_in_pdf": true,
          "page": 1,
          "source_type": "text",
          "confidence": "high",
          "extraction_plan": "Locate the 'Methods' section on page 1. The sentence 'The primary outcome was overall survival assessed in the intention-to-treat population.' explicitly states the primary endpoint.",
          "column_name_raw": null
        }
      ]
    },
    {
      "group_name": "Number of Arms Included",
      "columns": [
        {
          "column_index": 1,
          "column_name": "Number of Arms Included",
          "found_in_pdf": true,
          "page": 1,
          "source_type": "text",
          "confidence": "high",
          "extraction_plan": "The 'Methods' section on page 1 states that two phase 3 trials of the STAMPEDE platform protocol were analyzed. The 'Findings' section on page 1 and Figure 1 on page 4 detail the random assignment for each trial. The abiraterone trial had two arms: 'standard of care' and 'standard of care plus abiraterone'. The abiraterone and enzalutamide trial also had two arms: 'standard of care' and 'standard of care plus abiraterone and enzalutamide'. Since the text explicitly states 'no overlapping controls' for the two trials, the standard of care arms are distinct patient cohorts. Therefore, a total of 4 distinct arms were included in this analysis.",
          "column_name_raw": null
        }
      ]
    },
    {
      "group_name": "ORR - N (%)",
      "columns": [
        {
          "column_index": 1,
          "column_name": "ORR - N (%) | Treatment | Overall",
          "found_in_pdf": false,
          "page": -1,
          "source_type": "not_applicable",
          "confidence": "high",
          "extraction_plan": "Overall Response Rate (ORR) and its components (CR, SD, PD) are not reported in the provided PDF. The document focuses on outcomes such as overall survival, prostate cancer-specific survival, failure-free survival, metastatic progression-free survival, symptomatic skeletal-related events, and adverse events. I searched the text and tables on pages 1-14 for 'ORR', 'Overall Response Rate', 'Complete Response', 'Stable Disease', and 'Progressive Disease' as specific response metrics, but did not find this information reported in the requested format.",
          "column_name_raw": null
        },
        {
          "column_index": 2,
          "column_name": "ORR - N (%) | Treatment | CR",
          "found_in_pdf": false,
          "page": -1,
          "source_type": "not_applicable",
          "confidence": "high",
          "extraction_plan": "Complete Response (CR) as part of an Overall Response Rate (ORR) is not reported in the provided PDF. The document focuses on outcomes such as overall survival, prostate cancer-specific survival, failure-free survival, metastatic progression-free survival, symptomatic skeletal-related events, and adverse events. I searched the text and tables on pages 1-14 for 'ORR', 'Overall Response Rate', 'Complete Response', 'Stable Disease', and 'Progressive Disease' as specific response metrics, but did not find this information reported in the requested format.",
          "column_name_raw": null
        },
        {
          "column_index": 3,
          "column_name": "ORR - N (%) | Treatment | SD",
          "found_in_pdf": false,
          "page": -1,
          "source_type": "not_applicable",
          "confidence": "high",
          "extraction_plan": "Stable Disease (SD) as part of an Overall Response Rate (ORR) is not reported in the provided PDF. The document focuses on outcomes such as overall survival, prostate cancer-specific survival, failure-free survival, metastatic progression-free survival, symptomatic skeletal-related events, and adverse events. I searched the text and tables on pages 1-14 for 'ORR', 'Overall Response Rate', 'Complete Response', 'Stable Disease', and 'Progressive Disease' as specific response metrics, but did not find this information reported in the requested format.",
          "column_name_raw": null
        },
        {
          "column_index": 4,
          "column_name": "ORR - N (%) | Treatment | PD",
          "found_in_pdf": false,
          "page": -1,
          "source_type": "not_applicable",
          "confidence": "high",
          "extraction_plan": "Progressive Disease (PD) as part of an Overall Response Rate (ORR) is not reported in the provided PDF. While 'progression' is mentioned in the context of disease progression (e.g., page 11), it is not presented as a specific 'PD - N (%)' metric within an ORR framework. The document focuses on outcomes such as overall survival, prostate cancer-specific survival, failure-free survival, metastatic progression-free survival, symptomatic skeletal-related events, and adverse events. I searched the text and tables on pages 1-14 for 'ORR', 'Overall Response Rate', 'Complete Response', 'Stable Disease', and 'Progressive Disease' as specific response metrics, but did not find this information reported in the requested format.",
          "column_name_raw": null
        },
        {
          "column_index": 5,
          "column_name": "ORR - N (%) | Control | Overall",
          "found_in_pdf": false,
          "page": -1,
          "source_type": "not_applicable",
          "confidence": "high",
          "extraction_plan": "Overall Response Rate (ORR) and its components (CR, SD, PD) for the control group are not reported in the provided PDF. The document focuses on outcomes such as overall survival, prostate cancer-specific survival, failure-free survival, metastatic progression-free survival, symptomatic skeletal-related events, and adverse events. I searched the text and tables on pages 1-14 for 'ORR', 'Overall Response Rate', 'Complete Response', 'Stable Disease', and 'Progressive Disease' as specific response metrics, but did not find this information reported in the requested format.",
          "column_name_raw": null
        },
        {
          "column_index": 6,
          "column_name": "ORR - N (%) | Control | CR",
          "found_in_pdf": false,
          "page": -1,
          "source_type": "not_applicable",
          "confidence": "high",
          "extraction_plan": "Complete Response (CR) as part of an Overall Response Rate (ORR) for the control group is not reported in the provided PDF. The document focuses on outcomes such as overall survival, prostate cancer-specific survival, failure-free survival, metastatic progression-free survival, symptomatic skeletal-related events, and adverse events. I searched the text and tables on pages 1-14 for 'ORR', 'Overall Response Rate', 'Complete Response', 'Stable Disease', and 'Progressive Disease' as specific response metrics, but did not find this information reported in the requested format.",
          "column_name_raw": null
        },
        {
          "column_index": 7,
          "column_name": "ORR - N (%) | Control | SD",
          "found_in_pdf": false,
          "page": -1,
          "source_type": "not_applicable",
          "confidence": "high",
          "extraction_plan": "Stable Disease (SD) as part of an Overall Response Rate (ORR) for the control group is not reported in the provided PDF. The document focuses on outcomes such as overall survival, prostate cancer-specific survival, failure-free survival, metastatic progression-free survival, symptomatic skeletal-related events, and adverse events. I searched the text and tables on pages 1-14 for 'ORR', 'Overall Response Rate', 'Complete Response', 'Stable Disease', and 'Progressive Disease' as specific response metrics, but did not find this information reported in the requested format.",
          "column_name_raw": null
        },
        {
          "column_index": 8,
          "column_name": "ORR - N (%) | Control | PD",
          "found_in_pdf": false,
          "page": -1,
          "source_type": "not_applicable",
          "confidence": "high",
          "extraction_plan": "Progressive Disease (PD) as part of an Overall Response Rate (ORR) for the control group is not reported in the provided PDF. While 'progression' is mentioned in the context of disease progression (e.g., page 11), it is not presented as a specific 'PD - N (%)' metric within an ORR framework. The document focuses on outcomes such as overall survival, prostate cancer-specific survival, failure-free survival, metastatic progression-free survival, symptomatic skeletal-related events, and adverse events. I searched the text and tables on pages 1-14 for 'ORR', 'Overall Response Rate', 'Complete Response', 'Stable Disease', and 'Progressive Disease' as specific response metrics, but did not find this information reported in the requested format.",
          "column_name_raw": null
        }
      ]
    },
    {
      "group_name": "No. of Deaths - N",
      "columns": [
        {
          "column_index": 1,
          "column_name": "No. of Deaths - N | Treatment",
          "found_in_pdf": true,
          "page": 12,
          "source_type": "text",
          "confidence": "high",
          "extraction_plan": "Extract the number '521' from the text on page 12, which states: 'fewer deaths attributed to prostate cancer in patients who received abiraterone with or without enzalutamide than in those who received standard of care (413 [79%] of 521 in treatment groups vs 581 [88%] of 663 in standard of care groups)'.",
          "column_name_raw": null
        },
        {
          "column_index": 2,
          "column_name": "No. of Deaths - N | Control",
          "found_in_pdf": true,
          "page": 12,
          "source_type": "text",
          "confidence": "high",
          "extraction_plan": "Extract the number '663' from the text on page 12, which states: 'fewer deaths attributed to prostate cancer in patients who received abiraterone with or without enzalutamide than in those who received standard of care (413 [79%] of 521 in treatment groups vs 581 [88%] of 663 in standard of care groups)'.",
          "column_name_raw": null
        }
      ]
    },
    {
      "group_name": "PFS Rate (%)",
      "columns": [
        {
          "column_index": 1,
          "column_name": "PFS Rate (%) | Overall | Treatment",
          "found_in_pdf": false,
          "page": 9,
          "source_type": "not_applicable",
          "confidence": "low",
          "extraction_plan": "PFS rates as a single percentage at a specific time point are not explicitly reported in the text or tables. Progression-free survival curves are presented in Figure 4 (panels C, D, E, F) on page 9, and hazard ratios for PFS are discussed on page 11, but specific percentage rates at a defined time point for the overall treatment group are not provided.",
          "column_name_raw": null
        },
        {
          "column_index": 2,
          "column_name": "PFS Rate (%) | Overall | Control",
          "found_in_pdf": false,
          "page": 9,
          "source_type": "not_applicable",
          "confidence": "low",
          "extraction_plan": "PFS rates as a single percentage at a specific time point are not explicitly reported in the text or tables. Progression-free survival curves are presented in Figure 4 (panels C, D, E, F) on page 9, and hazard ratios for PFS are discussed on page 11, but specific percentage rates at a defined time point for the overall control group are not provided.",
          "column_name_raw": null
        }
      ]
    },
    {
      "group_name": "Quality of Life Scale",
      "columns": [
        {
          "column_index": 1,
          "column_name": "Quality of Life Scale",
          "found_in_pdf": false,
          "page": 4,
          "source_type": "not_applicable",
          "confidence": "high",
          "extraction_plan": "The 'Outcomes' section on page 4 lists the primary and secondary outcomes of the trials, including overall survival, prostate cancer-specific survival, failure-free survival, progression-free survival, metastatic progression-free survival, symptomatic skeletal-related events, toxic effects and adverse events, and cost-effectiveness. A 'Quality of Life Scale' or any related quality of life assessment is not mentioned as an outcome or a measured variable in this section or elsewhere in the provided text.",
          "column_name_raw": null
        }
      ]
    },
    {
      "group_name": "Quality of Life reported",
      "columns": [
        {
          "column_index": 1,
          "column_name": "Quality of Life reported",
          "found_in_pdf": false,
          "page": 4,
          "source_type": "not_applicable",
          "confidence": "high",
          "extraction_plan": "The PDF lists several outcomes in the 'Outcomes' section on page 4, including overall survival, prostate cancer-specific survival, failure-free survival, metastatic progression-free survival, symptomatic skeletal-related events, toxic effects and adverse events, and cost-effectiveness. However, 'Quality of Life' is not mentioned as one of the reported outcomes or assessed parameters in the document.",
          "column_name_raw": null
        }
      ]
    },
    {
      "group_name": "Metastases - N (%)",
      "columns": [
        {
          "column_index": 1,
          "column_name": "Metastases - N (%) | Liver | Treatment",
          "found_in_pdf": false,
          "page": 4,
          "source_type": "not_applicable",
          "confidence": "high",
          "extraction_plan": "The PDF mentions 'visceral disease' was assessed (page 4, Methods), which typically includes liver metastases. However, Table 1 (pages 5-6) only reports 'Metastatic volume' as 'Low', 'High', or 'Missing' and does not provide a breakdown of the number and percentage of patients with liver metastases in the treatment groups.",
          "column_name_raw": null
        },
        {
          "column_index": 2,
          "column_name": "Metastases - N (%) | Liver | Control",
          "found_in_pdf": false,
          "page": 4,
          "source_type": "not_applicable",
          "confidence": "high",
          "extraction_plan": "The PDF mentions 'visceral disease' was assessed (page 4, Methods), which typically includes liver metastases. However, Table 1 (pages 5-6) only reports 'Metastatic volume' as 'Low', 'High', or 'Missing' and does not provide a breakdown of the number and percentage of patients with liver metastases in the control groups.",
          "column_name_raw": null
        },
        {
          "column_index": 3,
          "column_name": "Metastases - N (%) | Lungs | Treatment",
          "found_in_pdf": false,
          "page": 4,
          "source_type": "not_applicable",
          "confidence": "high",
          "extraction_plan": "The PDF mentions 'visceral disease' was assessed (page 4, Methods), which typically includes lung metastases. However, Table 1 (pages 5-6) only reports 'Metastatic volume' as 'Low', 'High', or 'Missing' and does not provide a breakdown of the number and percentage of patients with lung metastases in the treatment groups.",
          "column_name_raw": null
        },
        {
          "column_index": 4,
          "column_name": "Metastases - N (%) | Lungs | Control",
          "found_in_pdf": false,
          "page": 4,
          "source_type": "not_applicable",
          "confidence": "high",
          "extraction_plan": "The PDF mentions 'visceral disease' was assessed (page 4, Methods), which typically includes lung metastases. However, Table 1 (pages 5-6) only reports 'Metastatic volume' as 'Low', 'High', or 'Missing' and does not provide a breakdown of the number and percentage of patients with lung metastases in the control groups.",
          "column_name_raw": null
        },
        {
          "column_index": 5,
          "column_name": "Metastases - N (%) | Bone | Treatment",
          "found_in_pdf": false,
          "page": 4,
          "source_type": "not_applicable",
          "confidence": "high",
          "extraction_plan": "The PDF states that 'bone metastases' were assessed (page 4, Methods). However, Table 1 (pages 5-6) only reports 'Metastatic volume' as 'Low', 'High', or 'Missing' and does not provide a breakdown of the number and percentage of patients with bone metastases in the treatment groups.",
          "column_name_raw": null
        },
        {
          "column_index": 6,
          "column_name": "Metastases - N (%) | Bone | Control",
          "found_in_pdf": false,
          "page": 4,
          "source_type": "not_applicable",
          "confidence": "high",
          "extraction_plan": "The PDF states that 'bone metastases' were assessed (page 4, Methods). However, Table 1 (pages 5-6) only reports 'Metastatic volume' as 'Low', 'High', or 'Missing' and does not provide a breakdown of the number and percentage of patients with bone metastases in the control groups.",
          "column_name_raw": null
        },
        {
          "column_index": 7,
          "column_name": "Metastases - N (%) | Nodal | Treatment",
          "found_in_pdf": false,
          "page": 5,
          "source_type": "not_applicable",
          "confidence": "high",
          "extraction_plan": "Table 1 (page 5) reports 'N stage (pelvic nodes)' with 'N+' (positive nodes) for two different treatment groups: 'Standard of care plus abiraterone' (293 [58%]) in the Abiraterone trial and 'Standard of care plus enzalutamide and abiraterone' (278 [60%]) in the Abiraterone and enzalutamide trial. Since the canonical column name does not specify which trial, the value is ambiguous and cannot be uniquely extracted.",
          "column_name_raw": null
        },
        {
          "column_index": 8,
          "column_name": "Metastases - N (%) | Nodal | Control",
          "found_in_pdf": false,
          "page": 5,
          "source_type": "not_applicable",
          "confidence": "high",
          "extraction_plan": "Table 1 (page 5) reports 'N stage (pelvic nodes)' with 'N+' (positive nodes) for two different control groups: 'Standard of care' (291 [58%]) in the Abiraterone trial and 'Standard of care' (278 [61%]) in the Abiraterone and enzalutamide trial. Since the canonical column name does not specify which trial, the value is ambiguous and cannot be uniquely extracted.",
          "column_name_raw": null
        }
      ]
    },
    {
      "group_name": "Secondary Endpoint(s)",
      "columns": [
        {
          "column_index": 1,
          "column_name": "Secondary Endpoint(s)",
          "found_in_pdf": true,
          "page": 4,
          "source_type": "text",
          "confidence": "high",
          "extraction_plan": "Extract the list of secondary outcomes from the 'Outcomes' section on page 4. These include: prostate cancer-specific survival; failure-free survival (biochemical failure, local or lymph node progression, distant metastases, or death from prostate cancer); progression-free survival (excluding biochemical failure); metastatic progression-free survival; symptomatic skeletal-related events; toxic effects and adverse events; and cost-effectiveness of research treatment.",
          "column_name_raw": null
        }
      ]
    },
    {
      "group_name": "Previous local therapy - N (%)",
      "columns": [
        {
          "column_index": 1,
          "column_name": "Previous local therapy - N (%) | Prostatectomy | Treatment",
          "found_in_pdf": false,
          "page": 6,
          "source_type": "not_applicable",
          "confidence": "high",
          "extraction_plan": "The PDF provides a 'Previous treatment to prostate (No, Yes)' row in Table 1 on page 6, but it does not break down the type of previous treatment into specific local therapies like prostatectomy. Therefore, this specific data point is not reported.",
          "column_name_raw": null
        },
        {
          "column_index": 2,
          "column_name": "Previous local therapy - N (%) | Prostatectomy | Control",
          "found_in_pdf": false,
          "page": 6,
          "source_type": "not_applicable",
          "confidence": "high",
          "extraction_plan": "The PDF provides a 'Previous treatment to prostate (No, Yes)' row in Table 1 on page 6, but it does not break down the type of previous treatment into specific local therapies like prostatectomy. Therefore, this specific data point is not reported.",
          "column_name_raw": null
        },
        {
          "column_index": 3,
          "column_name": "Previous local therapy - N (%) | Orchiectomy | Treatment",
          "found_in_pdf": false,
          "page": 6,
          "source_type": "not_applicable",
          "confidence": "high",
          "extraction_plan": "Table 1 on page 6 lists 'Orchiectomy' under 'Planned or current hormone therapy', which is part of the standard of care for the trial, not a 'Previous local therapy' performed before the trial. Therefore, this specific data point is not reported as a previous local therapy.",
          "column_name_raw": null
        },
        {
          "column_index": 4,
          "column_name": "Previous local therapy - N (%) | Orchiectomy | Control",
          "found_in_pdf": false,
          "page": 6,
          "source_type": "not_applicable",
          "confidence": "high",
          "extraction_plan": "Table 1 on page 6 lists 'Orchiectomy' under 'Planned or current hormone therapy', which is part of the standard of care for the trial, not a 'Previous local therapy' performed before the trial. Therefore, this specific data point is not reported as a previous local therapy.",
          "column_name_raw": null
        },
        {
          "column_index": 5,
          "column_name": "Previous local therapy - N (%) | Radiotherapy | Treatment",
          "found_in_pdf": false,
          "page": 6,
          "source_type": "not_applicable",
          "confidence": "high",
          "extraction_plan": "The PDF mentions 'Palliative radiotherapy planned as standard of care' in Table 1 on page 6 and 'planned radiotherapy as standard of care' as a stratification factor in the text on page 3. This refers to radiotherapy planned or administered during the trial for palliation, not a 'Previous local therapy' performed before the trial. Therefore, this specific data point is not reported.",
          "column_name_raw": null
        },
        {
          "column_index": 6,
          "column_name": "Previous local therapy - N (%) | Radiotherapy | Control",
          "found_in_pdf": false,
          "page": 6,
          "source_type": "not_applicable",
          "confidence": "high",
          "extraction_plan": "The PDF mentions 'Palliative radiotherapy planned as standard of care' in Table 1 on page 6 and 'planned radiotherapy as standard of care' as a stratification factor in the text on page 3. This refers to radiotherapy planned or administered during the trial for palliation, not a 'Previous local therapy' performed before the trial. Therefore, this specific data point is not reported.",
          "column_name_raw": null
        }
      ]
    },
    {
      "group_name": "Total Participants - N",
      "columns": [
        {
          "column_index": 1,
          "column_name": "Total Participants - N",
          "found_in_pdf": true,
          "page": 4,
          "source_type": "text",
          "confidence": "high",
          "extraction_plan": "Extract the total number of patients randomly assigned from the text on page 4, specifically '5488 patients randomly assigned (from Nov 15, 2011, to Jan 17, 2014, and from July 29, 2014, to March 31, 2016)'.",
          "column_name_raw": null
        }
      ]
    },
    {
      "group_name": "Race - N (%)",
      "columns": [
        {
          "column_index": 1,
          "column_name": "Race - N (%) | White | Treatment",
          "found_in_pdf": false,
          "page": 4,
          "source_type": "not_applicable",
          "confidence": "high",
          "extraction_plan": "Race or ethnicity data were not collected, as stated in the 'Methods' section on page 4: \"Race or ethnicity data were not collected.\"",
          "column_name_raw": null
        },
        {
          "column_index": 2,
          "column_name": "Race - N (%) | White | Control",
          "found_in_pdf": false,
          "page": 4,
          "source_type": "not_applicable",
          "confidence": "high",
          "extraction_plan": "Race or ethnicity data were not collected, as stated in the 'Methods' section on page 4: \"Race or ethnicity data were not collected.\"",
          "column_name_raw": null
        },
        {
          "column_index": 3,
          "column_name": "Race - N (%) | Black or African American | Treatment",
          "found_in_pdf": false,
          "page": 4,
          "source_type": "not_applicable",
          "confidence": "high",
          "extraction_plan": "Race or ethnicity data were not collected, as stated in the 'Methods' section on page 4: \"Race or ethnicity data were not collected.\"",
          "column_name_raw": null
        },
        {
          "column_index": 4,
          "column_name": "Race - N (%) | Black or African American | Control",
          "found_in_pdf": false,
          "page": 4,
          "source_type": "not_applicable",
          "confidence": "high",
          "extraction_plan": "Race or ethnicity data were not collected, as stated in the 'Methods' section on page 4: \"Race or ethnicity data were not collected.\"",
          "column_name_raw": null
        },
        {
          "column_index": 5,
          "column_name": "Race - N (%) | Asian | Treatment",
          "found_in_pdf": false,
          "page": 4,
          "source_type": "not_applicable",
          "confidence": "high",
          "extraction_plan": "Race or ethnicity data were not collected, as stated in the 'Methods' section on page 4: \"Race or ethnicity data were not collected.\"",
          "column_name_raw": null
        },
        {
          "column_index": 6,
          "column_name": "Race - N (%) | Asian | Control",
          "found_in_pdf": false,
          "page": 4,
          "source_type": "not_applicable",
          "confidence": "high",
          "extraction_plan": "Race or ethnicity data were not collected, as stated in the 'Methods' section on page 4: \"Race or ethnicity data were not collected.\"",
          "column_name_raw": null
        },
        {
          "column_index": 7,
          "column_name": "Race - N (%) | Nat. Hawaiian or Pac. Islander | Treatment",
          "found_in_pdf": false,
          "page": 4,
          "source_type": "not_applicable",
          "confidence": "high",
          "extraction_plan": "Race or ethnicity data were not collected, as stated in the 'Methods' section on page 4: \"Race or ethnicity data were not collected.\"",
          "column_name_raw": null
        },
        {
          "column_index": 8,
          "column_name": "Race - N (%) | Nat. Hawaiian or Pac. Islander | Control",
          "found_in_pdf": false,
          "page": 4,
          "source_type": "not_applicable",
          "confidence": "high",
          "extraction_plan": "Race or ethnicity data were not collected, as stated in the 'Methods' section on page 4: \"Race or ethnicity data were not collected.\"",
          "column_name_raw": null
        },
        {
          "column_index": 9,
          "column_name": "Race - N (%) | Amer. Indian or Alaska Nat. | Treatment",
          "found_in_pdf": false,
          "page": 4,
          "source_type": "not_applicable",
          "confidence": "high",
          "extraction_plan": "Race or ethnicity data were not collected, as stated in the 'Methods' section on page 4: \"Race or ethnicity data were not collected.\"",
          "column_name_raw": null
        },
        {
          "column_index": 10,
          "column_name": "Race - N (%) | Amer. Indian or Alaska Nat. | Control",
          "found_in_pdf": false,
          "page": 4,
          "source_type": "not_applicable",
          "confidence": "high",
          "extraction_plan": "Race or ethnicity data were not collected, as stated in the 'Methods' section on page 4: \"Race or ethnicity data were not collected.\"",
          "column_name_raw": null
        },
        {
          "column_index": 11,
          "column_name": "Race - N (%) | Other | Treatment",
          "found_in_pdf": false,
          "page": 4,
          "source_type": "not_applicable",
          "confidence": "high",
          "extraction_plan": "Race or ethnicity data were not collected, as stated in the 'Methods' section on page 4: \"Race or ethnicity data were not collected.\"",
          "column_name_raw": null
        },
        {
          "column_index": 12,
          "column_name": "Race - N (%) | Other | Control",
          "found_in_pdf": false,
          "page": 4,
          "source_type": "not_applicable",
          "confidence": "high",
          "extraction_plan": "Race or ethnicity data were not collected, as stated in the 'Methods' section on page 4: \"Race or ethnicity data were not collected.\"",
          "column_name_raw": null
        },
        {
          "column_index": 13,
          "column_name": "Race - N (%) | Unknown | Treatment",
          "found_in_pdf": false,
          "page": 4,
          "source_type": "not_applicable",
          "confidence": "high",
          "extraction_plan": "Race or ethnicity data were not collected, as stated in the 'Methods' section on page 4: \"Race or ethnicity data were not collected.\"",
          "column_name_raw": null
        },
        {
          "column_index": 14,
          "column_name": "Race - N (%) | Unknown | Control",
          "found_in_pdf": false,
          "page": 4,
          "source_type": "not_applicable",
          "confidence": "high",
          "extraction_plan": "Race or ethnicity data were not collected, as stated in the 'Methods' section on page 4: \"Race or ethnicity data were not collected.\"",
          "column_name_raw": null
        }
      ]
    },
    {
      "group_name": "Treatment Arm 1 Regimen",
      "columns": [
        {
          "column_index": 1,
          "column_name": "Treatment Arm 1 Regimen",
          "found_in_pdf": true,
          "page": 1,
          "source_type": "text",
          "confidence": "high",
          "extraction_plan": "Extract the description of the 'standard of care' regimen from the 'Methods' section on page 1. The regimen is: 'standard of care (androgen deprivation therapy; docetaxel 75 mg/m\b2 intravenously for six cycles with prednisolone 10 mg orally once per day allowed from Dec 17, 2015)'",
          "column_name_raw": null
        }
      ]
    },
    {
      "group_name": "Treatment Arm - N",
      "columns": [
        {
          "column_index": 1,
          "column_name": "Treatment Arm - N",
          "found_in_pdf": true,
          "page": 5,
          "source_type": "table",
          "confidence": "high",
          "extraction_plan": "Extract the N values from the column headers of Table 1 on pages 5 and 6. The values are: Abiraterone trial: Standard of care (n=502), Abiraterone trial: Standard of care plus abiraterone (n=501), Abiraterone and enzalutamide trial: Standard of care (n=454), Abiraterone and enzalutamide trial: Standard of care plus enzalutamide and abiraterone (n=462).",
          "column_name_raw": null
        }
      ]
    },
    {
      "group_name": "PS - N (%)",
      "columns": [
        {
          "column_index": 1,
          "column_name": "PS - N (%) | 0 | Treatment",
          "found_in_pdf": true,
          "page": 5,
          "source_type": "table",
          "confidence": "high",
          "extraction_plan": "Extract the value '376 (75%)' from Table 1, page 5, under the row 'WHO performance status: 0' and column 'Abiraterone trial: Standard of care plus abiraterone (n=501)'. Data for the Abiraterone and Enzalutamide trial's treatment arm is also available as '325 (70%)'.",
          "column_name_raw": null
        },
        {
          "column_index": 2,
          "column_name": "PS - N (%) | 0 | Control",
          "found_in_pdf": true,
          "page": 5,
          "source_type": "table",
          "confidence": "high",
          "extraction_plan": "Extract the value '370 (74%)' from Table 1, page 5, under the row 'WHO performance status: 0' and column 'Abiraterone trial: Standard of care (n=502)'. Data for the Abiraterone and Enzalutamide trial's control arm is also available as '315 (69%)'.",
          "column_name_raw": null
        },
        {
          "column_index": 3,
          "column_name": "PS - N (%) | 1-2 | Treatment",
          "found_in_pdf": true,
          "page": 5,
          "source_type": "table",
          "confidence": "high",
          "extraction_plan": "Calculate by summing the N and % values for 'WHO performance status: 1' and 'WHO performance status: 2' from Table 1, page 5, under the column 'Abiraterone trial: Standard of care plus abiraterone (n=501)'. For status 1: 118 (24%), for status 2: 7 (1%). The sum is 125 (25%). Data for the Abiraterone and Enzalutamide trial's treatment arm (status 1: 129 (28%), status 2: 8 (2%)) sums to 137 (30%).",
          "column_name_raw": null
        },
        {
          "column_index": 4,
          "column_name": "PS - N (%) | 1-2 | Control",
          "found_in_pdf": true,
          "page": 5,
          "source_type": "table",
          "confidence": "high",
          "extraction_plan": "Calculate by summing the N and % values for 'WHO performance status: 1' and 'WHO performance status: 2' from Table 1, page 5, under the column 'Abiraterone trial: Standard of care (n=502)'. For status 1: 125 (25%), for status 2: 7 (1%). The sum is 132 (26%). Data for the Abiraterone and Enzalutamide trial's control arm (status 1: 134 (30%), status 2: 5 (1%)) sums to 139 (31%).",
          "column_name_raw": null
        }
      ]
    },
    {
      "group_name": "TTPSA (mo)",
      "columns": [
        {
          "column_index": 1,
          "column_name": "TTPSA (mo) | Treatment",
          "found_in_pdf": false,
          "page": 4,
          "source_type": "not_applicable",
          "confidence": "high",
          "extraction_plan": "The document mentions \"PSA progression (biochemical failure)\" as an outcome (page 3, 4), which is part of the composite endpoint \"failure-free survival\" (Figure 4C, 4D). However, the median time specifically for \"PSA progression\" (TTPSA) for the treatment group is not reported in the text, tables, or figures.",
          "column_name_raw": null
        },
        {
          "column_index": 2,
          "column_name": "TTPSA (mo) | Control",
          "found_in_pdf": false,
          "page": 4,
          "source_type": "not_applicable",
          "confidence": "high",
          "extraction_plan": "The document mentions \"PSA progression (biochemical failure)\" as an outcome (page 3, 4), which is part of the composite endpoint \"failure-free survival\" (Figure 4C, 4D). However, the median time specifically for \"PSA progression\" (TTPSA) for the control group is not reported in the text, tables, or figures.",
          "column_name_raw": null
        }
      ]
    },
    {
      "group_name": "Trial",
      "columns": [
        {
          "column_index": 1,
          "column_name": "Trial",
          "found_in_pdf": true,
          "page": 1,
          "source_type": "text",
          "confidence": "high",
          "extraction_plan": "Extract the name \"STAMPEDE platform protocol\" from the article title and abstract on page 1, where it is described as \"two randomised phase 3 trials of the STAMPEDE platform protocol\".",
          "column_name_raw": null
        }
      ]
    },
    {
      "group_name": "Treatment Arm(s)",
      "columns": [
        {
          "column_index": 1,
          "column_name": "Treatment Arm(s)",
          "found_in_pdf": true,
          "page": 1,
          "source_type": "text",
          "confidence": "high",
          "extraction_plan": "Extract the names of the treatment arms from the 'Methods' and 'Findings' sections on page 1. The arms are: 'standard of care', 'standard of care plus abiraterone acetate 1000 mg and prednisolone 5 mg', and 'abiraterone acetate and prednisolone plus enzalutamide 160 mg'. The text also specifies which trial each arm belongs to (abiraterone trial or abiraterone and enzalutamide trial). Tables 1 on pages 5 and 6 also list these treatment arms as column headers.",
          "column_name_raw": null
        }
      ]
    },
    {
      "group_name": "Region - N (%)",
      "columns": [
        {
          "column_index": 1,
          "column_name": "Region - N (%) | North America | Treatment",
          "found_in_pdf": false,
          "page": -1,
          "source_type": "not_applicable",
          "confidence": "high",
          "extraction_plan": "The provided PDF describes study sites in the UK and Switzerland (pages 1, 2, 3) and explicitly states that race or ethnicity data were not collected (page 4). No information on patient numbers by region (e.g., North America) or treatment group is reported in the text, tables (pages 5, 6, 10), or figures (pages 8, 9).",
          "column_name_raw": null
        },
        {
          "column_index": 2,
          "column_name": "Region - N (%) | North America | Control",
          "found_in_pdf": false,
          "page": -1,
          "source_type": "not_applicable",
          "confidence": "high",
          "extraction_plan": "The provided PDF describes study sites in the UK and Switzerland (pages 1, 2, 3) and explicitly states that race or ethnicity data were not collected (page 4). No information on patient numbers by region (e.g., North America) or control group is reported in the text, tables (pages 5, 6, 10), or figures (pages 8, 9).",
          "column_name_raw": null
        },
        {
          "column_index": 3,
          "column_name": "Region - N (%) | South America | Treatment",
          "found_in_pdf": false,
          "page": -1,
          "source_type": "not_applicable",
          "confidence": "high",
          "extraction_plan": "The provided PDF describes study sites in the UK and Switzerland (pages 1, 2, 3) and explicitly states that race or ethnicity data were not collected (page 4). No information on patient numbers by region (e.g., South America) or treatment group is reported in the text, tables (pages 5, 6, 10), or figures (pages 8, 9).",
          "column_name_raw": null
        },
        {
          "column_index": 4,
          "column_name": "Region - N (%) | South America | Control",
          "found_in_pdf": false,
          "page": -1,
          "source_type": "not_applicable",
          "confidence": "high",
          "extraction_plan": "The provided PDF describes study sites in the UK and Switzerland (pages 1, 2, 3) and explicitly states that race or ethnicity data were not collected (page 4). No information on patient numbers by region (e.g., South America) or control group is reported in the text, tables (pages 5, 6, 10), or figures (pages 8, 9).",
          "column_name_raw": null
        },
        {
          "column_index": 5,
          "column_name": "Region - N (%) | Europe | Treatment",
          "found_in_pdf": false,
          "page": -1,
          "source_type": "not_applicable",
          "confidence": "high",
          "extraction_plan": "The study was conducted at 117 sites in the UK and Switzerland (pages 1, 2, 3). While these are European countries, the PDF does not provide a breakdown of patient numbers (N (%)) specifically for 'Europe' as a region or for treatment groups. The text explicitly states that race or ethnicity data were not collected (page 4). No such regional breakdown is found in the tables (pages 5, 6, 10) or figures (pages 8, 9).",
          "column_name_raw": null
        },
        {
          "column_index": 6,
          "column_name": "Region - N (%) | Europe | Control",
          "found_in_pdf": false,
          "page": -1,
          "source_type": "not_applicable",
          "confidence": "high",
          "extraction_plan": "The study was conducted at 117 sites in the UK and Switzerland (pages 1, 2, 3). While these are European countries, the PDF does not provide a breakdown of patient numbers (N (%)) specifically for 'Europe' as a region or for control groups. The text explicitly states that race or ethnicity data were not collected (page 4). No such regional breakdown is found in the tables (pages 5, 6, 10) or figures (pages 8, 9).",
          "column_name_raw": null
        },
        {
          "column_index": 7,
          "column_name": "Region - N (%) | Africa | Treatment",
          "found_in_pdf": false,
          "page": -1,
          "source_type": "not_applicable",
          "confidence": "high",
          "extraction_plan": "The provided PDF describes study sites in the UK and Switzerland (pages 1, 2, 3) and explicitly states that race or ethnicity data were not collected (page 4). No information on patient numbers by region (e.g., Africa) or treatment group is reported in the text, tables (pages 5, 6, 10), or figures (pages 8, 9).",
          "column_name_raw": null
        },
        {
          "column_index": 8,
          "column_name": "Region - N (%) | Africa | Control",
          "found_in_pdf": false,
          "page": -1,
          "source_type": "not_applicable",
          "confidence": "high",
          "extraction_plan": "The provided PDF describes study sites in the UK and Switzerland (pages 1, 2, 3) and explicitly states that race or ethnicity data were not collected (page 4). No information on patient numbers by region (e.g., Africa) or control group is reported in the text, tables (pages 5, 6, 10), or figures (pages 8, 9).",
          "column_name_raw": null
        },
        {
          "column_index": 9,
          "column_name": "Region - N (%) | Asia | Treatment",
          "found_in_pdf": false,
          "page": -1,
          "source_type": "not_applicable",
          "confidence": "high",
          "extraction_plan": "The provided PDF describes study sites in the UK and Switzerland (pages 1, 2, 3) and explicitly states that race or ethnicity data were not collected (page 4). No information on patient numbers by region (e.g., Asia) or treatment group is reported in the text, tables (pages 5, 6, 10), or figures (pages 8, 9).",
          "column_name_raw": null
        },
        {
          "column_index": 10,
          "column_name": "Region - N (%) | Asia | Control",
          "found_in_pdf": false,
          "page": -1,
          "source_type": "not_applicable",
          "confidence": "high",
          "extraction_plan": "The provided PDF describes study sites in the UK and Switzerland (pages 1, 2, 3) and explicitly states that race or ethnicity data were not collected (page 4). No information on patient numbers by region (e.g., Asia) or control group is reported in the text, tables (pages 5, 6, 10), or figures (pages 8, 9).",
          "column_name_raw": null
        },
        {
          "column_index": 11,
          "column_name": "Region - N (%) | Oceania | Treatment",
          "found_in_pdf": false,
          "page": -1,
          "source_type": "not_applicable",
          "confidence": "high",
          "extraction_plan": "The provided PDF describes study sites in the UK and Switzerland (pages 1, 2, 3) and explicitly states that race or ethnicity data were not collected (page 4). No information on patient numbers by region (e.g., Oceania) or treatment group is reported in the text, tables (pages 5, 6, 10), or figures (pages 8, 9).",
          "column_name_raw": null
        },
        {
          "column_index": 12,
          "column_name": "Region - N (%) | Oceania | Control",
          "found_in_pdf": false,
          "page": -1,
          "source_type": "not_applicable",
          "confidence": "high",
          "extraction_plan": "The provided PDF describes study sites in the UK and Switzerland (pages 1, 2, 3) and explicitly states that race or ethnicity data were not collected (page 4). No information on patient numbers by region (e.g., Oceania) or control group is reported in the text, tables (pages 5, 6, 10), or figures (pages 8, 9).",
          "column_name_raw": null
        }
      ]
    },
    {
      "group_name": "Reporting by prognostic groups - Y/N",
      "columns": [
        {
          "column_index": 1,
          "column_name": "Reporting by prognostic groups - Y/N | Synchronous",
          "found_in_pdf": false,
          "page": 3,
          "source_type": "not_applicable",
          "confidence": "high",
          "extraction_plan": "The PDF describes eligibility criteria for patients with advanced prostate cancer, including those who relapsed after primary treatment (page 3). However, it does not explicitly define or report outcomes separately for 'synchronous' (metastatic at initial diagnosis) versus 'metachronous' (metastases developing later) disease as distinct prognostic groups in the main results or subgroup analyses. The paper focuses on 'metastatic prostate cancer' generally.",
          "column_name_raw": null
        },
        {
          "column_index": 2,
          "column_name": "Reporting by prognostic groups - Y/N | Metachronous",
          "found_in_pdf": false,
          "page": 3,
          "source_type": "not_applicable",
          "confidence": "high",
          "extraction_plan": "The PDF describes eligibility criteria for patients with advanced prostate cancer, including those who relapsed after primary treatment (page 3). However, it does not explicitly define or report outcomes separately for 'synchronous' (metastatic at initial diagnosis) versus 'metachronous' (metastases developing later) disease as distinct prognostic groups in the main results or subgroup analyses. The paper focuses on 'metastatic prostate cancer' generally.",
          "column_name_raw": null
        },
        {
          "column_index": 3,
          "column_name": "Reporting by prognostic groups - Y/N | High volume",
          "found_in_pdf": true,
          "page": 5,
          "source_type": "table",
          "confidence": "high",
          "extraction_plan": "Reported in Table 1 on page 5 under 'Metastatic volume' as a baseline characteristic. The text on page 5 also states that 'outcomes split by low-volume and high-volume disease are of interest and were included as an additional prespecified subgroup analysis'. Figure 3 (panels D and E) on page 8 and Figure 4 (panels C, D, E, F) on page 9 show subgroup analyses and efficacy endpoints split by high-volume metastatic disease.",
          "column_name_raw": null
        },
        {
          "column_index": 4,
          "column_name": "Reporting by prognostic groups - Y/N | Low volume",
          "found_in_pdf": true,
          "page": 5,
          "source_type": "table",
          "confidence": "high",
          "extraction_plan": "Reported in Table 1 on page 5 under 'Metastatic volume' as a baseline characteristic. The text on page 5 also states that 'outcomes split by low-volume and high-volume disease are of interest and were included as an additional prespecified subgroup analysis'. Figure 3 (panels D and E) on page 8 and Figure 4 (panels C, D, E, F) on page 9 show subgroup analyses and efficacy endpoints split by low-volume metastatic disease.",
          "column_name_raw": null
        }
      ]
    },
    {
      "group_name": "Treatment Class",
      "columns": [
        {
          "column_index": 1,
          "column_name": "Treatment Class",
          "found_in_pdf": true,
          "page": 1,
          "source_type": "text",
          "confidence": "high",
          "extraction_plan": "The different treatment classes are explicitly defined in the 'Methods' section on page 1, where patients were randomly assigned to 'standard of care', 'standard of care plus abiraterone acetate and prednisolone', or 'abiraterone acetate and prednisolone plus enzalutamide'. These classes are consistently used throughout the document, including as column headers in Table 1 on pages 5 and 6.",
          "column_name_raw": null
        }
      ]
    },
    {
      "group_name": "Type of Therapy",
      "columns": [
        {
          "column_index": 1,
          "column_name": "Type of Therapy",
          "found_in_pdf": true,
          "page": 6,
          "source_type": "table",
          "confidence": "high",
          "extraction_plan": "Extract the row 'Planned or current hormone therapy' and its sub-rows ('Orchiectomy', 'Luteinising hormone-releasing hormone agonists or antagonists', 'Bicalutamide', 'Maximum androgen blockade') along with the corresponding values for each treatment arm from Table 1 on page 6.",
          "column_name_raw": null
        }
      ]
    },
    {
      "group_name": "OS Rate (%)",
      "columns": [
        {
          "column_index": 1,
          "column_name": "OS Rate (%) | Overall | Treatment",
          "found_in_pdf": true,
          "page": 9,
          "source_type": "text",
          "confidence": "high",
          "extraction_plan": "Extract '48%' from text on page 9, in the 'overall survival' section, referring to the abiraterone trial at 84 months for 'standard of care plus abiraterone'.",
          "column_name_raw": null
        },
        {
          "column_index": 2,
          "column_name": "OS Rate (%) | Overall | Control",
          "found_in_pdf": true,
          "page": 9,
          "source_type": "text",
          "confidence": "high",
          "extraction_plan": "Extract '30%' from text on page 9, in the 'overall survival' section, referring to the abiraterone trial at 84 months for 'standard of care'.",
          "column_name_raw": null
        },
        {
          "column_index": 3,
          "column_name": "OS Rate (%) | Synchronous | Treatment",
          "found_in_pdf": false,
          "page": 5,
          "source_type": "not_applicable",
          "confidence": "high",
          "extraction_plan": "The term 'synchronous' is not used to categorize OS rates in the text or figures. The closest breakdown is by 'metastatic volume' (low/high) or 'N stage' (pelvic nodes), but not specifically 'synchronous' vs 'metachronous' for OS rates. Looked in text on pages 1-5, and tables/figures on pages 5, 6, 8, 9.",
          "column_name_raw": null
        },
        {
          "column_index": 4,
          "column_name": "OS Rate (%) | Synchronous | Control",
          "found_in_pdf": false,
          "page": 5,
          "source_type": "not_applicable",
          "confidence": "high",
          "extraction_plan": "The term 'synchronous' is not used to categorize OS rates in the text or figures. The closest breakdown is by 'metastatic volume' (low/high) or 'N stage' (pelvic nodes), but not specifically 'synchronous' vs 'metachronous' for OS rates. Looked in text on pages 1-5, and tables/figures on pages 5, 6, 8, 9.",
          "column_name_raw": null
        },
        {
          "column_index": 5,
          "column_name": "OS Rate (%) | Metachronous | Treatment",
          "found_in_pdf": false,
          "page": 3,
          "source_type": "not_applicable",
          "confidence": "high",
          "extraction_plan": "While the methods section (page 3) mentions eligibility for patients who relapsed after primary treatment (which could imply metachronous disease), OS rates are not specifically broken down by 'metachronous' disease. Looked in text on pages 1-5, and tables/figures on pages 5, 6, 8, 9.",
          "column_name_raw": null
        },
        {
          "column_index": 6,
          "column_name": "OS Rate (%) | Metachronous | Control",
          "found_in_pdf": false,
          "page": 3,
          "source_type": "not_applicable",
          "confidence": "high",
          "extraction_plan": "While the methods section (page 3) mentions eligibility for patients who relapsed after primary treatment (which could imply metachronous disease), OS rates are not specifically broken down by 'metachronous' disease. Looked in text on pages 1-5, and tables/figures on pages 5, 6, 8, 9.",
          "column_name_raw": null
        },
        {
          "column_index": 7,
          "column_name": "OS Rate (%) | High volume | Treatment",
          "found_in_pdf": true,
          "page": 7,
          "source_type": "figure",
          "confidence": "medium",
          "extraction_plan": "Estimate the overall survival rate at 84 months from Figure 2E, 'Overall survival (%)' for 'high-volume metastatic disease' in the Abiraterone trial, 'Standard of care plus abiraterone' curve. The rate is approximately 42%.",
          "column_name_raw": null
        },
        {
          "column_index": 8,
          "column_name": "OS Rate (%) | High volume | Control",
          "found_in_pdf": true,
          "page": 7,
          "source_type": "figure",
          "confidence": "medium",
          "extraction_plan": "Estimate the overall survival rate at 84 months from Figure 2E, 'Overall survival (%)' for 'high-volume metastatic disease' in the Abiraterone trial, 'Standard of care' curve. The rate is approximately 22%.",
          "column_name_raw": null
        },
        {
          "column_index": 9,
          "column_name": "OS Rate (%) | Low volume | Treatment",
          "found_in_pdf": true,
          "page": 7,
          "source_type": "figure",
          "confidence": "medium",
          "extraction_plan": "Estimate the overall survival rate at 84 months from Figure 2C, 'Overall survival (%)' for 'low-volume metastatic disease' in the Abiraterone trial, 'Standard of care plus abiraterone' curve. The rate is approximately 62%.",
          "column_name_raw": null
        },
        {
          "column_index": 10,
          "column_name": "OS Rate (%) | Low volume | Control",
          "found_in_pdf": true,
          "page": 7,
          "source_type": "figure",
          "confidence": "medium",
          "extraction_plan": "Estimate the overall survival rate at 84 months from Figure 2C, 'Overall survival (%)' for 'low-volume metastatic disease' in the Abiraterone trial, 'Standard of care' curve. The rate is approximately 42%.",
          "column_name_raw": null
        }
      ]
    },
    {
      "group_name": "Volume of disease - N (%)",
      "columns": [
        {
          "column_index": 1,
          "column_name": "Volume of disease - N (%) | High | Treatment",
          "found_in_pdf": true,
          "page": 5,
          "source_type": "table",
          "confidence": "high",
          "extraction_plan": "Extract the value from Table 1, page 5, under the 'Abiraterone trial' section, in the 'Standard of care plus abiraterone (n=501)' column, for the row 'Metastatic volume: High'. The value is 253 (51%). Note: 'Treatment' is interpreted as the 'Standard of care plus abiraterone' arm of the Abiraterone trial, as it is the first treatment group listed in the table.",
          "column_name_raw": "High"
        },
        {
          "column_index": 2,
          "column_name": "Volume of disease - N (%) | High | Control",
          "found_in_pdf": true,
          "page": 5,
          "source_type": "table",
          "confidence": "high",
          "extraction_plan": "Extract the value from Table 1, page 5, under the 'Abiraterone trial' section, in the 'Standard of care (n=502)' column, for the row 'Metastatic volume: High'. The value is 271 (54%). Note: 'Control' is interpreted as the 'Standard of care' arm of the Abiraterone trial, as it is the first control group listed in the table.",
          "column_name_raw": "High"
        },
        {
          "column_index": 3,
          "column_name": "Volume of disease - N (%) | Low | Control",
          "found_in_pdf": true,
          "page": 5,
          "source_type": "table",
          "confidence": "high",
          "extraction_plan": "Extract the value from Table 1, page 5, under the 'Abiraterone trial' section, in the 'Standard of care (n=502)' column, for the row 'Metastatic volume: Low'. The value is 204 (41%). Note: 'Control' is interpreted as the 'Standard of care' arm of the Abiraterone trial, as it is the first control group listed in the table.",
          "column_name_raw": "Low"
        }
      ]
    }
  ]
}